static_refl/__init__.py
static_refl/core.py
static_refl/json.py
static_refl/options.py
static_refl/serde_common.py
static_refl/utils.py
static_refl-0.1.0.dist-info/METADATA
static_refl-0.1.0.dist-info/WHEEL
static_refl-0.1.0.dist-info/entry_points.txt
static_refl-0.1.0.dist-info/licenses/LICENSE
static_refl-0.1.0.dist-info/RECORD
