Metadata-Version: 2.4
Name: static-refl
Version: 0.1.0
Summary: Add your description here
Author-email: thautwarm <twshere@outlook.com>
License-File: LICENSE
Requires-Python: >=3.12.5
Requires-Dist: casefy>=1.1.0
Provides-Extra: dev
Requires-Dist: pytest>=8.0.0; extra == 'dev'
